[
  {
    "name": "api-tool-555",
    "version": "1.0.6",
    "desc": "An advanced auto-evolving library for api development.",
    "score": 93.64,
    "tag": "api",
    "timestamp": "2025-12-16T01:45:56.800212"
  },
  {
    "name": "django-tool-845",
    "version": "1.6.1",
    "desc": "An advanced auto-evolving library for django development.",
    "score": 92.5,
    "tag": "django",
    "timestamp": "2025-12-16T01:45:56.800252"
  },
  {
    "name": "django-tool-563",
    "version": "1.8.9",
    "desc": "An advanced auto-evolving library for django development.",
    "score": 91.86,
    "tag": "django",
    "timestamp": "2025-12-16T01:45:56.800248"
  },
  {
    "name": "api-tool-578",
    "version": "1.4.9",
    "desc": "An advanced auto-evolving library for api development.",
    "score": 91.14,
    "tag": "api",
    "timestamp": "2025-12-16T01:45:56.800221"
  },
  {
    "name": "python-tool-558",
    "version": "1.6.3",
    "desc": "An advanced auto-evolving library for python development.",
    "score": 84.69,
    "tag": "python",
    "timestamp": "2025-12-16T01:45:56.800182"
  },
  {
    "name": "machine-learning-tool-575",
    "version": "1.8.0",
    "desc": "An advanced auto-evolving library for machine-learning development.",
    "score": 42.03,
    "tag": "machine-learning",
    "timestamp": "2025-12-16T01:45:56.800206"
  },
  {
    "name": "automation-tool-982",
    "version": "1.9.5",
    "desc": "An advanced auto-evolving library for automation development.",
    "score": 41.2,
    "tag": "automation",
    "timestamp": "2025-12-16T01:45:56.800234"
  },
  {
    "name": "rust-tool-650",
    "version": "1.0.7",
    "desc": "An advanced auto-evolving library for rust development.",
    "score": 32.15,
    "tag": "rust",
    "timestamp": "2025-12-16T01:45:56.800200"
  },
  {
    "name": "automation-tool-738",
    "version": "1.7.0",
    "desc": "An advanced auto-evolving library for automation development.",
    "score": 24.02,
    "tag": "automation",
    "timestamp": "2025-12-16T01:45:56.800229"
  },
  {
    "name": "api-tool-922",
    "version": "1.5.2",
    "desc": "An advanced auto-evolving library for api development.",
    "score": 18.41,
    "tag": "api",
    "timestamp": "2025-12-16T01:45:56.800217"
  },
  {
    "name": "automation-tool-473",
    "version": "1.0.5",
    "desc": "An advanced auto-evolving library for automation development.",
    "score": 7.01,
    "tag": "automation",
    "timestamp": "2025-12-16T01:45:56.800238"
  },
  {
    "name": "python-tool-704",
    "version": "1.0.4",
    "desc": "An advanced auto-evolving library for python development.",
    "score": 3.99,
    "tag": "python",
    "timestamp": "2025-12-16T01:45:56.800192"
  },
  {
    "name": "django-tool-290",
    "version": "1.6.3",
    "desc": "An advanced auto-evolving library for django development.",
    "score": 3.5,
    "tag": "django",
    "timestamp": "2025-12-16T01:45:56.800243"
  }
]